{"title":"Materials for drug capture: Filtering off-target chemotherapy agents from the bloodstream","uri":"","abstract":"The systemic, off-target toxicity of chemotherapy is a well-known problem in oncol. In an effort to overcome this challenge, many approaches have been developed to deliver chemotherapy directly and exclusively the tumor. One of these approaches is transarterial chemoembolization (TACE), a procedure in which chemotherapy is introduced via catheter directly into the artery supplying the tumor. Despite this sitespecific delivery, a portion of the chemotherapy dose still enters systemic circulation and causes off-target damage. To address this issue, we are developing materials that are capable of capturing this residual chemotherapy from the blood stream. Ultimately, this material will be used to construct a device that can be deployed via catheter \"downstream\" from the tumor, enabling excess chemotherapy to be sequestered before entering systemic circulation. Our approach uses DNA-functionalized surfaces, which enables the capture of DNA-targeting chemotherapy drugs. In order to improve the cost and scalability of this system, we developed simple methods of covalently attaching genomic DNA to a variety of surfaces. We have further demonstrated that this approach is capable of sequestering doxorubicin, cisplatin, and epirubicin-three common chemotherapy agents-from soln. at clin. relevant concns. The efficacy of these materials was demonstrated in PBS, human serum, and blood, indicating that this approach is likely viable in vivo. Moreover, the kinetics of drug capture are rapid: We obsd. \u003e95% redn. of doxorubicin concn. in human serum in \u003c10 min. The efficacy of these materials indicates that drug capture is indeed a viable strategy for mitigating the harmful side-effects assocd. with chemotherapy.","documents":[{"id":"http://authors.library.caltech.edu/id/document/251690","docid":251690,"rev_number":3,"files":[{"id":"http://authors.library.caltech.edu/id/file/1253236","fileid":1253236,"datasetid":"document","objectid":251690,"filename":"Schulz_2017pPOLY-281.pdf","mime_type":"application/pdf","hash":"a0d11b4b3f43b8f344f1e965f696e189","hash_type":"MD5","filesize":91423,"mtime":"2017-05-03 22:48:00","url":"http://authors.library.caltech.edu/77177/1/Schulz_2017pPOLY-281.pdf"}],"eprintid":77177,"pos":1,"placement":1,"mime_type":"application/pdf","format":"application/pdf","language":"en","security":"internal","license":"other","main":"Schulz_2017pPOLY-281.pdf","content":"published"}],"note":"© 2017 American Chemical Society.","id":77177,"rev_number":8,"userid":18,"eprint_dir":"disk0/00/07/71/77","datestamp":"2017-05-04 01:13:14","lastmod":"2017-05-04 01:13:14","status_changed":"2017-05-04 01:13:14","type":"conference_item","metadata_visibility":"show","creators":[{"given":"Michael D.","family":"Schulz","id":"Schulz-M-D","orcid":""},{"given":"Carl","family":"Blumenfeld","id":"Blumenfeld-C-M","orcid":""},{"given":"Steven","family":"Hetts","id":"Hetts-S","orcid":""},{"given":"Robert H.","family":"Grubbs","id":"Grubbs-R-H","orcid":"0000-0002-0057-7817"}],"ispublished":"pub","subjects":null,"full_text_status":"none","keywords":"","date":"2017-04","date_type":"published","publication":"","volume":"","number":"","pagerange":"POLY-281","id_number":"CaltechAUTHORS:20170503-154754407","refereed":true,"issn":"","official_url":"http://resolver.caltech.edu/CaltechAUTHORS:20170503-154754407","related_url":[{"url":"https://www.acs.org/content/acs/en/meetings/spring-2017.html","type":"org","description":"Conference Website"}],"referencetext":null,"rights":"No commercial reproduction, distribution, display or performance rights in this work are provided.","official_citation":"","other_numbering_system":null,"funders":null,"collection":"CaltechAUTHORS","reviewer":"GP","local_group":null}