{"title":"Fabrication and Replication of Polymer Integrated Optical Devices Using Electron-Beam Lithography and Soft Lithography","uri":"","abstract":"Polymeric integrated optical devices, including microring resonator optical filters and Mach−Zehnder interferometer modulators, fabricated by electron-beam lithography and soft lithography are considered in this article. Microring resonator optical filters made of SU-8 (MicroChem, Newton, MA), directly patterned by electron-beam lithography, demonstrate that SU-8 is a good candidate for high-precision, easily fabricated, and good-optical-quality passive integrated optical devices. Due to the electron-beam lithography process, the coupling between the straight waveguide and the microring resonator is precisely controlled, and the critical coupling condition can be achieved. Additionally, films containing several devices patterned by electron-beam lithography are peeled from the silicon substrate, yielding ultrathin all-polymer flexible free-standing microring resonator optical filters exhibiting up to −27 dB filtering extinction. Using a PDMS stamp, molded from these electron-beam-patterned microring resonator optical filters, identical replicas are fabricated by the soft lithography molding technique. Soft lithography is also applied to active polymer materials. A short 2-mm active-section prototype Mach−Zehnder interferometer modulator is made by the replica molding process, using CLD-1/APC electrooptic polymer as the core material. A reasonable intensity-modulation effect is observed by applying voltage to one arm of the interferometer.","documents":[{"id":"http://authors.library.caltech.edu/id/document/252236","docid":252236,"rev_number":3,"files":[{"id":"http://authors.library.caltech.edu/id/file/1257569","fileid":1257569,"datasetid":"document","objectid":252236,"filename":"jp049724d.pdf","mime_type":"application/pdf","hash":"39b144e52f5c9e98265ef4ae1ff0a89d","hash_type":"MD5","filesize":457062,"mtime":"2017-05-15 22:16:15","url":"http://authors.library.caltech.edu/77467/1/jp049724d.pdf"}],"eprintid":77467,"pos":1,"placement":1,"mime_type":"application/pdf","format":"application/pdf","language":"en","security":"internal","license":"other","main":"jp049724d.pdf","content":"published"}],"note":"© 2004 American Chemical Society. \n\nReceived: January 19, 2004. Publication Date (Web): May 1, 2004. \n\nThe authors thank J. Poon, Dr. J. Scheuer, Dr. R. Lee, Prof. S. Mookherjea, W. Green, and J. Choi for kind help and fruitful discussion. The work is supported by the National Science Foundation (DMR-0120967) and the Defense Advanced Research Projects Agency (N00014-04-1-0094).","id":77467,"rev_number":8,"userid":18,"eprint_dir":"disk0/00/07/74/67","datestamp":"2017-05-16 03:21:56","lastmod":"2017-05-16 03:21:56","status_changed":"2017-05-16 03:21:56","type":"article","metadata_visibility":"show","creators":[{"given":"Yanyi","family":"Huang","id":"Huang-Yanyi","orcid":""},{"given":"George T.","family":"Paloczi","id":"Paloczi-G-T","orcid":""},{"given":"Amnon","family":"Yariv","id":"Yariv-A","orcid":""},{"given":"Cheng","family":"Zhang","id":"Zhang-Cheng","orcid":""},{"given":"Larry R.","family":"Dalton","id":"Dalton-L-R","orcid":""}],"ispublished":"pub","subjects":null,"full_text_status":"none","keywords":"","date":"2004-06-24","date_type":"published","publication":"Journal of Physical Chemistry B","volume":"108","number":"25","pagerange":"8606-8613","id_number":"CaltechAUTHORS:20170515-151610525","refereed":true,"issn":"1520-6106","official_url":"http://resolver.caltech.edu/CaltechAUTHORS:20170515-151610525","related_url":[{"url":"http://dx.doi.org/10.1021/jp049724d","type":"doi","description":"Article"},{"url":"http://pubs.acs.org/doi/abs/10.1021/jp049724d","type":"pub","description":"Article"}],"referencetext":["(1) Eldada, L.; Shacklette, L. W.  IEEE J. Select. Top. Quantum Electron. 2000, 6, 54.[CrossRef], [CAS]\n\n\n\n\n\n\n\n\n\n\n\nOpenURL CALIFORNIA INST OF TECHNOLOGY \n\n(2) Ma, H.; Jen, A. K.-Y.; Dalton, L. R.  Adv. Mater. 2002, 14, 1339.[CrossRef], [CAS]\n\n\n\n\n\n\n\n\n\n\n\nOpenURL CALIFORNIA INST OF TECHNOLOGY \n\n(3) Eldada, L.; Blomquist, R.; Shacklette, L. W.; McFarland, M. J.  Opt. Eng. 2000, 39, 596.[CrossRef], [CAS]\n\n\n\n\n\n\n\n\n\n\n\nOpenURL CALIFORNIA INST OF TECHNOLOGY \n\n(4) For example, see:  Zhao, Y. G.; Lu, W. K.; Ma, Y.; Kim, S. S.; Ho, S. T.; Marks, T. J.  Appl. Phys. Lett. 2000, 77, 2961.[CrossRef], [CAS]\n\n\n\n\n\n\n\n\n\n\n\nOpenURL CALIFORNIA INST OF TECHNOLOGY \n\n(5) For example, see:  Enami, Y.; Meredith, G.; Peyghambarian, N.; Jen, A. K.-Y.  Appl. Phys. Lett. 2003, 83, 4692.[CrossRef], [CAS]\n\n\n\n\n\n\n\n\n\n\n\nOpenURL CALIFORNIA INST OF TECHNOLOGY \n\n(6) (a) Xia, Q.; Keimel, C.; Ge, H.; Yu, Z.; Wu, W.; Chou, S. Y.  Appl. Phys. Lett. 2003, 83, 4417.[CrossRef], [CAS]\n\n\n\n\n\n\n\n\n\n\n\nOpenURL CALIFORNIA INST OF TECHNOLOGY (b) Chao, C.; Guo, L. J.  J. Vac. Sci. Technol. B 2002, 20, 2862.[CrossRef], [CAS]\n\n\n\n\n\n\n\n\n\n\n\nOpenURL CALIFORNIA INST OF TECHNOLOGY (c) Mizuno, H.; Sugihara, O.; Kaino, T.; Okamoto, N.; Hosino, M.  Opt. Lett. 2003, 28, 2378.[CrossRef], [PubMed], [CAS]\n\n\n\n\n\n\n\n\n\n\n\nOpenURL CALIFORNIA INST OF TECHNOLOGY \n\n(7) For example, see:  (a) Xia, Y.; Whitesides, G. M.  Annu. Rev. Mater. Sci. 1998, 28, 153. (b) Xia, Y.; Whitesides, G. M. Angew Chem. Int. Ed. 1998, 37, 550. (c) Xia, Y.; Rogers, J. A.; Paul, K. E.; Whitesides, G. M. Chem. Rev. 1999, 99, 1823. (d) Xia, Y.; Kim, E.; Zhao, X.-M.; Rogers, J. A.; Prentiss, M.; Whitesides, G. M. Science 1996, 273, 347.[CrossRef], [CAS]\n\n\n\n\n\n\n\n\n\n\n\nOpenURL CALIFORNIA INST OF TECHNOLOGY \n\n(8) (a) Wijekoon, W. M. K. P.; Prasad, P. N. Nonlinear Optical Preperties of Polymers. In Physical Properties of Polymers Handbook; Mark, J. E., Ed.; AIP Press:  New York, 1996.\n\n\nOpenURL CALIFORNIA INST OF TECHNOLOGY (b) Dalton, L. R.; Sterer, W. H.; Robinson, B. H.; Zhang, C.; Ren, A.; Garner, S.; Chen, A.; Londergan, T.; Irwin, L.; Carlson, B.; Fifield, L.; Phelan, G.; Kincaid, C.; Amend, J.; Jen, A.  J. Mater. Chem. 1999, 9, 1905.[CrossRef], [CAS]\n\n\n\n\n\n\n\n\n\n\n\nOpenURL CALIFORNIA INST OF TECHNOLOGY (c) Dalton, L.  Adv. Polym. Sci. 2003, 158, 1.[CrossRef]\n\n\nOpenURL CALIFORNIA INST OF TECHNOLOGY (d) Kajzar, F.; Lee, K.-S.; Jen, A. K.-Y.  Adv. Polym. Sci. 2003, 161, 1.[CrossRef], [CAS]\n\n\n\n\n\n\n\n\n\n\n\nOpenURL CALIFORNIA INST OF TECHNOLOGY (e) Dalton, L. R.  J. Phys. Condens. Matter 2003, 15, R897.[CrossRef], [CAS]\n\n\n\n\n\n\n\n\n\n\n\nOpenURL CALIFORNIA INST OF TECHNOLOGY \n\n(9) For example, see:  Wong, W. H.; Zhou, J.; Pun, E. Y. B.  Appl. Phys. Lett. 2001, 78, 2110.[CrossRef], [CAS]\n\n\n\n\n\n\n\n\n\n\n\nOpenURL CALIFORNIA INST OF TECHNOLOGY \n\n(a) Zhao, X. M.; Smith, S. P.; Waldman, S. J.; Whitesides, G. M.; Prentiss, M.  Appl. Phys. Lett. 1997, 71, 1017.[CrossRef], [CAS]\n\n\n\n\n\n\n\n\n\n\n\nOpenURL CALIFORNIA INST OF TECHNOLOGY (b) Rogers, J. A.; Meier, M.; Dodabalapur, A.  Appl. Phys. Lett. 1998, 73, 1766.[CrossRef], [CAS]\n\n\n\n\n\n\n\n\n\n\n\nOpenURL CALIFORNIA INST OF TECHNOLOGY (c) Rogers, J. A.; Meier, M.; Dodabalapur, A.; Laskowski, E. J.; Capppuzzo, M. A.  Appl. Phys. Lett. 1999, 74, 3257.[CrossRef], [CAS]\n\n\n\n\n\n\n\n\n\n\n\nOpenURL CALIFORNIA INST OF TECHNOLOGY \n\n(11) Quake, S. R.; Scherer, A.  Science 2000, 290, 1536.[CrossRef], [PubMed], [CAS]\n\n\n\n\n\n\n\n\n\n\n\nOpenURL CALIFORNIA INST OF TECHNOLOGY \n\n(12) (a) Yariv, A.  Electron. Lett. 2000, 36, 321.[CrossRef], [CAS]\n\n\n\n\n\n\n\n\n\n\n\nOpenURL CALIFORNIA INST OF TECHNOLOGY (b) Yariv A.  IEEE Photonics Technol. Lett. 2002, 14, 483.[CrossRef]\n\n\nOpenURL CALIFORNIA INST OF TECHNOLOGY (c) Madsen, C. K.; Zhao, J. H.  Optical Filter Design and Analysis:  A Signal Processing Approach; John Wiley \u0026 Sons:  New York, 1999.\n\n\nOpenURL CALIFORNIA INST OF TECHNOLOGY \n\n(13) (a) Rabiei, P.; Steier, W. H.; Zhang, C.; Dalton, L. R.  J. Lightwave Technol. 2002, 20, 1968.[CrossRef]\n\n\nOpenURL CALIFORNIA INST OF TECHNOLOGY (b) Paloczi, G. T.; Huang, Y.; Yariv, A.  Electron. Lett. 2003, 39, 1650.[CrossRef], [CAS]\n\n\n\n\n\n\n\n\n\n\n\nOpenURL CALIFORNIA INST OF TECHNOLOGY (c) Huang, Y.; Paloczi, G. T.; Scheuer, J.; Yariv, A.  Opt. Express 2003, 11, 2452.[CrossRef], [PubMed], [CAS]\n\n\n\n\n\n\n\n\n\n\n\nOpenURL CALIFORNIA INST OF TECHNOLOGY (d) Paloczi, G. T.; Huang, Y.; Yariv, A.; Mookherjea, S.  Opt. Express 2003, 11, 2666.[CrossRef], [PubMed], [CAS]\n\n\n\n\n\n\n\n\n\n\n\nOpenURL CALIFORNIA INST OF TECHNOLOGY \n\n(14) (a) Zhang, C.; Ren, A. S.; Wang, F.; Zhu, J.; Dalton, L. R.  Chem. Mater. 1999, 11, 1966.[ACS Full Text ACS Full Text], [CAS]\n\n\n\n\n\n\n\n\n\n\n\nOpenURL CALIFORNIA INST OF TECHNOLOGY (b) Shi, Y.; Zhang, C.; Zhang, H.; Bechtel, J. H.; Dalton, L. R.; Robinson, B. H.; Sterer, W. H.  Science 2000, 288, 119.[CrossRef], [PubMed], [CAS]\n\n\n\n\n\n\n\n\n\n\n\nOpenURL CALIFORNIA INST OF TECHNOLOGY (c) Shi, Y.; Lin, W.; Olson, D. J.; Bechtel, J. H.; Zhang, H.; Steier, W. H.; Zhang, C.; Dalton, L. R.  Appl. Phys. Lett. 2000, 77, 1.[CrossRef], [CAS]\n\n\n\n\n\n\n\n\n\n\n\nOpenURL CALIFORNIA INST OF TECHNOLOGY (d) Oh, M.-C.; Zhang, H.; Zhang, C.; Erlig, H.; Chang, Y.; Tsap, B.; Chang, D.; Szep, A.; Steier, W. H.; Fetterman, H. R.; Dalton, L. R.  IEEE J. Select. Top. Quantum Electron. 2001, 7, 826.[CrossRef], [CAS]\n\n\n\n\n\n\n\n\n\n\n\nOpenURL CALIFORNIA INST OF TECHNOLOGY \n\n(15) Malaquin, L.; Vieu, C. Using PDMS as a Thermocurable Resist for a Mold Assisted Imprint Process. In Alternative Lithography:  Unleashing the Potentials of Nanotechnology; Torres, C. M. S., Ed.; Kluwer Academic Publishers:  Boston, 2003.\n\n\nOpenURL CALIFORNIA INST OF TECHNOLOGY \n\n(16) Paloczi, G. T.; Huang, Y.; Yariv, A. Submitted.\n\n\nOpenURL CALIFORNIA INST OF TECHNOLOGY \n\n(17) Song, H.-C.; Oh, M.-C.; Ahn, S.-W.; Steier, W. H.; Fetterman, H. R.; Zhang, C.  Appl. Phys. Lett. 2003, 82, 4432.[CrossRef], [CAS]\n\n\n\n\n\n\n\n\n\n\n\nOpenURL CALIFORNIA INST OF TECHNOLOGY \n\n(18) Robinson, B. H.; Dalton, L. R.  J. Phys. Chem. A 2000, 104, 4785.[ACS Full Text ACS Full Text], [CAS]\n\n\n\n\n\n\n\n\n\n\n\nOpenURL CALIFORNIA INST OF TECHNOLOGY \n\n(19) (a) An, D.; Shi, Z.; Sun, L.; Taboada, J. M.; Zhou, Q.; Lu, X.; Chen, R. T.; Tang, S.; Zhang, H.; Steier, W. H.; Ren, A.; Dalton, L. R.  Appl. Phys. Lett. 2000, 76, 1972.[CrossRef], [CAS]\n\n\n\n\n\n\n\n\n\n\n\nOpenURL CALIFORNIA INST OF TECHNOLOGY (b) Ahn, S.-W.; Steier, W. H.; Kuo, Y.-H.; Oh, M.-C.; Lee, H.-J.; Zhang, C.; Fetterman, H. R.  Opt. Lett. 2002, 27, 2109.[CrossRef], [PubMed], [CAS]\n\n\n\n\n\n\n\n\n\n\n\nOpenURL CALIFORNIA INST OF TECHNOLOGY (c) Lee, M.; Katz, H. E.; Erben, C.; Gill, D. M.; Gopalan, P.; Heber, J. D.; McGee, D. J.  Science 2002, 298, 1401.\n"],"rights":"No commercial reproduction, distribution, display or performance rights in this work are provided.","official_citation":"Fabrication and Replication of Polymer Integrated Optical Devices Using Electron-Beam Lithography and Soft Lithography\nYanyi Huang, George T. Paloczi, Amnon Yariv, Cheng Zhang, and Larry R. Dalton\nThe Journal of Physical Chemistry B 2004 108 (25), 8606-8613 \nDOI: 10.1021/jp049724d","other_numbering_system":null,"funders":[{"agency":"NSF","grant_number":"DMR-0120967"},{"agency":"Defense Advanced Research Projects Agency (DARPA)","grant_number":""},{"agency":"Office of Naval Research (ONR)","grant_number":"N00014-04-1-0094"}],"collection":"CaltechAUTHORS","reviewer":"GP","local_group":null}